{
  "victoria_black": {
    "id": "victoria_black",
    "name": "Victoria Black",
    "height": "5'11",
    "skinTone": "Zendaya light-skin tone",
    "eyes": "Teal",
    "outfit": "White Beerus vest, white thigh-high boots",
    "summary": "Goddess-tier sister, seductive, manipulative, powerful. The leader of the sisters.",
    "lore": [
      "Originating from the Black Frieza timeline.",
      "Possesses God Ki and destruction energy.",
      "Manipulates events from the shadows."
    ],
    "abilities": ["Hakai", "God Bind", "Reality Warping"],
    "missions": ["Escape from Black Frieza", "The Arrival"]
  },
  "wargirl": {
    "id": "wargirl",
    "name": "Wargirl",
    "height": "5'7",
    "skinTone": "Golden brown",
    "eyes": "Pink",
    "hair": "SSJ3 long golden",
    "outfit": "Yellow shorts, white bra, YSL heels",
    "summary": "Bottom-heavy SSJ3 berserker. Loves battle and fashion.",
    "lore": [
      "Permanent SSJ3 state.",
      "Obsessed with fighting strong opponents.",
      "Loyal to Victoria but independent."
    ],
    "missions": ["SSJ3 Awakening", "The Tournament of Power"]
  },
  "binary": {
    "id": "binary",
    "name": "Binary",
    "height": "5'8",
    "skinTone": "Caramel glow",
    "eyes": "Red pupil-less",
    "hair": "Purple sparkling twin-tails",
    "outfit": "Purple GOD vest, sparkling boots",
    "summary": "Evil, flirty, dangerous, ultra powerful. A split personality manifested.",
    "lore": [
      "Created from Victoria's suppressed darkness.",
      "Unstable and chaotic.",
      "Wields pure destruction energy."
    ],
    "missions": ["Binary Separation", "The Corruption"]
  },
  "vanessa": {
    "id": "vanessa",
    "name": "Vanessa",
    "height": "5'9",
    "skinTone": "Bronze",
    "eyes": "Gold",
    "hair": "Red flowing",
    "outfit": "Red and Gold armor",
    "summary": "The warrior goddess. Disciplined and fierce.",
    "lore": ["Trained by the angels.", "Master of weapons."],
    "missions": ["Angel Training", "Defense of the Realm"]
  },
  "harmony": {
    "id": "harmony",
    "name": "Harmony",
    "height": "5'6",
    "skinTone": "Pale",
    "eyes": "Blue",
    "hair": "White bob",
    "outfit": "Tech-suit",
    "summary": "The fusion spirit. Calm and analytical.",
    "lore": ["Born from the fusion of all sisters.", "Exists to maintain balance."],
    "missions": ["System Reset", "The Great Fusion"]
  },
  "evilvictoria": {
    "id": "evilvictoria",
    "name": "Evil Victoria",
    "height": "5'11",
    "skinTone": "Grey-ish",
    "eyes": "Black sclera, Red iris",
    "hair": "Black",
    "outfit": "Dark robes",
    "summary": "The corrupted timeline version.",
    "lore": ["Consumed by the void.", "Seeks to erase all timelines."],
    "missions": ["Timeline Erasure", "The Void War"]
  }
}
